{"linha":"397-1 - GRAMADO","numero":"397-1","obs":"397-1 - GRAMADO","empresa":"COTALCAMP","ida":{"letreiro":"ESPECIAL","tempo":"24 a 36","extensao":8,"itinerario":["R DR RICARDO","R SEBASTIAO DE SOUZA","R ONZE DE AGOSTO","AV DR CAMPOS SALES","AV FRANCISCO GLICERIO","AV DR MORAES SALLES","ROD DR HEITOR PENTEADO (SP-81)","AV PAPA JOAO PAULO I","R NABIHA WAQUIM ABRAHAO","AL DOS FLAMBOYANT","AL DOS CAMBARAS","AL DAS TIPUANAS","R ELIZEU TEIXEIRA DE CAMARGO"],"horarios":{"util":["05:44","05:58","06:04","06:10","06:16","06:22","06:28","06:34","06:40","06:46","06:52","06:58","07:04","07:10","07:16","07:22","07:28","07:34","07:40","07:46","07:52","07:58","08:04","08:10","08:16","15:30","15:42","15:54","16:06","16:18","16:30","16:42","16:54","17:06","17:18","17:30","17:42","17:54","18:06","18:18"],"sabado":null,"domingo":null},"veiculos":{"util":21,"sabado":0,"domingo":0}},"volta":{"letreiro":"GRAMADO","tempo":"24 a 36","extensao":8,"itinerario":null,"horarios":{"util":["05:16","05:30","05:36","05:42","05:48","05:54","06:00","06:06","06:12","06:18","06:24","06:30","06:36","06:42","06:48","06:54","07:00","07:06","07:12","07:18","07:24","07:30","07:36","07:42","07:48","07:54","08:00","08:06","08:12","08:18","08:24","08:30","08:36","16:00","16:12","16:24","16:36","16:48","17:00","17:12","17:24","17:36","17:48"],"sabado":null,"domingo":null},"veiculos":{"util":21,"sabado":0,"domingo":0}}}